playground_pypi_package_f/__init__.py
playground_pypi_package_f-0.1.5.dist-info/METADATA
playground_pypi_package_f-0.1.5.dist-info/WHEEL
playground_pypi_package_f-0.1.5.dist-info/top_level.txt
playground_pypi_package_f-0.1.5.dist-info/RECORD
